clippy/__init__.py
clippy/clippy_types.py
clippy/config.py
clippy/constants.py
clippy/error.py
clippy/selectors.py
clippy/utils.py
clippy/backends/__init__.py
clippy/backends/serialization.py
clippy/backends/version.py
clippy/backends/fs/__init__.py
clippy/backends/fs/config.py
clippy/backends/fs/constants.py
clippy/backends/fs/execution.py
llnl_clippy-0.5.1.dist-info/METADATA
llnl_clippy-0.5.1.dist-info/WHEEL
llnl_clippy-0.5.1.dist-info/top_level.txt
llnl_clippy-0.5.1.dist-info/RECORD
