Metadata-Version: 2.4
Name: llnl-clippy
Version: 0.5.1
Summary: A Python interface to HPC resources
Author: Roger Pearce, Seth Bromberger
Project-URL: Homepage, https://github.com/LLNL/clippy
Project-URL: Issues, https://github.com/LLNL/clippy/issues
Classifier: Development Status :: 3 - Alpha
Classifier: Programming Language :: Python :: 3
Classifier: Programming Language :: C++
Classifier: Intended Audience :: Science/Research
Classifier: License :: OSI Approved :: MIT License
Classifier: Operating System :: OS Independent
Requires-Python: >=3.10
Requires-Dist: semver>=3.0
Requires-Dist: jsonlogic-py==0.2.1
Provides-Extra: dev
Requires-Dist: coverage; extra == "dev"
Requires-Dist: ruff; extra == "dev"
Requires-Dist: mypy; extra == "dev"
Requires-Dist: pytest; extra == "dev"
Requires-Dist: json-logic-qubit; extra == "dev"
